gmaps/__init__.py
gmaps/client.py
gmaps/compat.py
gmaps/directions.py
gmaps/distance_matrix.py
gmaps/elevation.py
gmaps/errors.py
gmaps/geocoding.py
gmaps/polyline.py
gmaps/status.py
gmaps/timezone.py
python_gmaps-0.3.1.dist-info/DESCRIPTION.rst
python_gmaps-0.3.1.dist-info/METADATA
python_gmaps-0.3.1.dist-info/RECORD
python_gmaps-0.3.1.dist-info/WHEEL
python_gmaps-0.3.1.dist-info/metadata.json
python_gmaps-0.3.1.dist-info/top_level.txt
